sms_pilot/__init__.py
sms_pilot/callback.py
sms_pilot/exception.py
sms_pilot/objects.py
sms_pilot/sender.py
sms_pilot_py-0.3.dist-info/LICENSE.md
sms_pilot_py-0.3.dist-info/METADATA
sms_pilot_py-0.3.dist-info/WHEEL
sms_pilot_py-0.3.dist-info/top_level.txt
sms_pilot_py-0.3.dist-info/RECORD
