Metadata-Version: 2.1
Name: sms-pilot-py
Version: 0.3
Summary: Python SMSPilot API
Home-page: https://github.com/migelbd/SmsPilotPy
Author: Mikhail Badrazhan
Author-email: migel.bd@gmail.com
License: MIT
Platform: UNKNOWN
Classifier: Programming Language :: Python :: 3
Classifier: License :: OSI Approved :: MIT License
Classifier: Operating System :: OS Independent
Requires-Python: >=3.6
Requires-Dist: requests
